libcsce/__init__.py
libcsce/bin/__init__.py
libcsce/bin/csce.py
libcsce/bin/list_cs_settings.py
libcsce/error.py
libcsce/parser.py
libcsce/setting.py
libcsce/typing.py
libcsce/utils.py
libcsce-0.1.0.dist-info/entry_points.txt
libcsce-0.1.0.dist-info/LICENSE
libcsce-0.1.0.dist-info/WHEEL
libcsce-0.1.0.dist-info/METADATA
libcsce-0.1.0.dist-info/RECORD
