Metadata-Version: 2.1
Name: libcsce
Version: 0.1.0
Summary: Cobalt Strike configuration extractor and parser library and scripts.
Home-page: https://github.com/strozfriedberg/cobaltstrike-config-extractor
License: Apache-2.0
Keywords: malware,rem,cobalt strike,parser
Author: Noah Rubin
Author-email: noah.rubin@strozfriedberg.com
Requires-Python: >=3.6,<4.0
Classifier: License :: OSI Approved :: Apache Software License
Classifier: Programming Language :: Python :: 3
Classifier: Programming Language :: Python :: 3.6
Classifier: Programming Language :: Python :: 3.7
Classifier: Programming Language :: Python :: 3.8
Classifier: Programming Language :: Python :: 3.9
Requires-Dist: pefile (>=2019.4.18)
Project-URL: Repository, https://github.com/strozfriedberg/cobaltstrike-config-extractor
